mymemopy/__init__.py
mymemopy/exceptions.py
mymemopy/request_api.py
mymemopy/text_wrapper.py
mymemopy/translator.py
mymemopy/users.py
mymemopy/utils/__init__.py
mymemopy/utils/languages_support.py
mymemopy/utils/time_parse.py
mymemopy-0.1.1.dist-info/LICENSE
mymemopy-0.1.1.dist-info/METADATA
mymemopy-0.1.1.dist-info/WHEEL
mymemopy-0.1.1.dist-info/RECORD
