Metadata-Version: 2.1
Name: mymemopy
Version: 0.1.1
Summary: Translate phrases or texts using the Mymemory API in a simple way.
Home-page: https://github.com/kurotom/MyMemoPy
License: GPL-3.0-or-later
Keywords: translator,translation,api,Mymemory API,simple
Author: kurotom
Author-email: 55354389+kurotom@users.noreply.github.com
Requires-Python: >=3.7,<4.0
Classifier: License :: OSI Approved :: GNU General Public License v3 or later (GPLv3+)
Classifier: Operating System :: OS Independent
Classifier: Programming Language :: Python :: 3
Classifier: Programming Language :: Python :: 3.7
Classifier: Programming Language :: Python :: 3.8
Classifier: Programming Language :: Python :: 3.9
Classifier: Programming Language :: Python :: 3.10
Classifier: Programming Language :: Python :: 3.11
Classifier: Topic :: Software Development
Classifier: Topic :: Software Development :: Build Tools
Requires-Dist: requests (>=2.31.0,<3.0.0)
Requires-Dist: terminal-in-colors (>=0.1.3,<0.2.0)
Project-URL: Bug Tracker, https://github.com/kurotom/MyMemoPy/issues
Project-URL: Repository, https://github.com/kurotom/MyMemoPy
